scicm/__init__.py
scicm/cm.py
scicm/tools.py
scicm/cm_data/B2P.txt
scicm/cm_data/B2T.txt
scicm/cm_data/BG.txt
scicm/cm_data/BM.txt
scicm/cm_data/BO.txt
scicm/cm_data/BR.txt
scicm/cm_data/BT.txt
scicm/cm_data/BY.txt
scicm/cm_data/BgreyY.txt
scicm/cm_data/BkG.txt
scicm/cm_data/BkO.txt
scicm/cm_data/BkR.txt
scicm/cm_data/BkT.txt
scicm/cm_data/BkY.txt
scicm/cm_data/Blue.txt
scicm/cm_data/Blue2080.txt
scicm/cm_data/BwG.txt
scicm/cm_data/BwM.txt
scicm/cm_data/BwO.txt
scicm/cm_data/BwR.txt
scicm/cm_data/Cyan.txt
scicm/cm_data/Day.txt
scicm/cm_data/G2Y.txt
scicm/cm_data/GB.txt
scicm/cm_data/GP.txt
scicm/cm_data/GT.txt
scicm/cm_data/Garnet.txt
scicm/cm_data/GkM.txt
scicm/cm_data/GkP.txt
scicm/cm_data/Green.txt
scicm/cm_data/Green2080.txt
scicm/cm_data/GwM.txt
scicm/cm_data/GwP.txt
scicm/cm_data/M2R.txt
scicm/cm_data/MB.txt
scicm/cm_data/MO.txt
scicm/cm_data/MR.txt
scicm/cm_data/MY.txt
scicm/cm_data/Magenta.txt
scicm/cm_data/Magenta2080.txt
scicm/cm_data/Night.txt
scicm/cm_data/O2Y.txt
scicm/cm_data/OB.txt
scicm/cm_data/OP.txt
scicm/cm_data/OT.txt
scicm/cm_data/OkM.txt
scicm/cm_data/Orange.txt
scicm/cm_data/Orange2080.txt
scicm/cm_data/P2M.txt
scicm/cm_data/PG.txt
scicm/cm_data/PM.txt
scicm/cm_data/PO.txt
scicm/cm_data/PR.txt
scicm/cm_data/PT.txt
scicm/cm_data/PY.txt
scicm/cm_data/PgreyG.txt
scicm/cm_data/PkM.txt
scicm/cm_data/PkO.txt
scicm/cm_data/PkR.txt
scicm/cm_data/PkY.txt
scicm/cm_data/Purple.txt
scicm/cm_data/Purple2080.txt
scicm/cm_data/PwM.txt
scicm/cm_data/Quartile.txt
scicm/cm_data/R2O.txt
scicm/cm_data/RB.txt
scicm/cm_data/RP.txt
scicm/cm_data/RT.txt
scicm/cm_data/Red.txt
scicm/cm_data/Red2080.txt
scicm/cm_data/RgreyB.txt
scicm/cm_data/Ripe.txt
scicm/cm_data/RwM.txt
scicm/cm_data/RwP.txt
scicm/cm_data/SoftBlue.txt
scicm/cm_data/SoftGreen.txt
scicm/cm_data/SoftMagenta.txt
scicm/cm_data/SoftOrange.txt
scicm/cm_data/SoftPurple.txt
scicm/cm_data/SoftRed.txt
scicm/cm_data/SoftTeal.txt
scicm/cm_data/SoftYellow.txt
scicm/cm_data/Stone.txt
scicm/cm_data/T2G.txt
scicm-1.0.6.dist-info/LICENSE
scicm-1.0.6.dist-info/METADATA
scicm-1.0.6.dist-info/WHEEL
scicm-1.0.6.dist-info/top_level.txt
scicm-1.0.6.dist-info/RECORD
