Metadata-Version: 2.1
Name: scicm
Version: 1.0.6
Summary: Science Colour Maps is a small package containing several colour maps created using viscm.
Home-page: https://github.com/MBravoS/scicm
Author: Matías A. Bravo Santa Cruz
Author-email: matias.bravo@icrar.org
License: BSD-3-Clause
License-File: LICENSE
Requires-Dist: requests
Requires-Dist: matplotlib >=3.7
Requires-Dist: setuptools >=45.0.0
